[{"name":"New Year's Day","date":{"month":1,"day":1},"formattedDate":"1 Jan","weekday":{"numeric":2,"name":"Tuesday"},"is_public":false,"is_observed":false,"is_religious":false,"type":"national holiday"},{"name":"March Equinox","date":{"month":3,"day":19},"formattedDate":"19 Mar","weekday":{"numeric":3,"name":"Wednesday"},"is_public":false,"is_observed":false,"is_religious":false,"type":"season"},{"name":"Maundy Thursday","date":{"month":3,"day":20},"formattedDate":"20 Mar","weekday":{"numeric":4,"name":"Thursday"},"is_public":false,"is_observed":false,"is_religious":true,"type":"national holiday, christian"},{"name":"Good Friday","date":{"month":3,"day":21},"formattedDate":"21 Mar","weekday":{"numeric":5,"name":"Friday"},"is_public":false,"is_observed":false,"is_religious":true,"type":"national holiday, christian"},{"name":"Easter Saturday","date":{"month":3,"day":22},"formattedDate":"22 Mar","weekday":{"numeric":6,"name":"Saturday"},"is_public":false,"is_observed":false,"is_religious":true,"type":"national holiday, christian"},{"name":"Easter Sunday","date":{"month":3,"day":23},"formattedDate":"23 Mar","weekday":{"numeric":7,"name":"Sunday"},"is_public":false,"is_observed":true,"is_religious":true,"type":"observance, christian"},{"name":"Easter Monday","date":{"month":3,"day":24},"formattedDate":"24 Mar","weekday":{"numeric":1,"name":"Monday"},"is_public":false,"is_observed":true,"is_religious":true,"type":"observance, christian"},{"name":"Labor Day","date":{"month":5,"day":1},"formattedDate":"1 May","weekday":{"numeric":4,"name":"Thursday"},"is_public":false,"is_observed":false,"is_religious":false,"type":"national holiday"},{"name":"Mothers’ Day (Working Mothers Only)","date":{"month":5,"day":10},"formattedDate":"10 May","weekday":{"numeric":6,"name":"Saturday"},"is_public":false,"is_observed":false,"is_religious":false,"type":"national holiday"},{"name":"June Solstice","date":{"month":6,"day":20},"formattedDate":"20 Jun","weekday":{"numeric":5,"name":"Friday"},"is_public":false,"is_observed":false,"is_religious":false,"type":"season"},{"name":"Army Day Holiday","date":{"month":6,"day":30},"formattedDate":"30 Jun","weekday":{"numeric":1,"name":"Monday"},"is_public":false,"is_observed":false,"is_religious":false,"type":"national holiday"},{"name":"Assumption of Mary (Guatemala City only)","date":{"month":8,"day":15},"formattedDate":"15 Aug","weekday":{"numeric":5,"name":"Friday"},"is_public":false,"is_observed":false,"is_religious":false,"type":"municipal holiday"},{"name":"Independence Day","date":{"month":9,"day":15},"formattedDate":"15 Sep","weekday":{"numeric":1,"name":"Monday"},"is_public":false,"is_observed":false,"is_religious":false,"type":"national holiday"},{"name":"September Equinox","date":{"month":9,"day":22},"formattedDate":"22 Sep","weekday":{"numeric":1,"name":"Monday"},"is_public":false,"is_observed":false,"is_religious":false,"type":"season"},{"name":"Dia de la raza","date":{"month":10,"day":12},"formattedDate":"12 Oct","weekday":{"numeric":7,"name":"Sunday"},"is_public":false,"is_observed":false,"is_religious":false,"type":"national holiday"},{"name":"Revolution of 1944","date":{"month":10,"day":20},"formattedDate":"20 Oct","weekday":{"numeric":1,"name":"Monday"},"is_public":false,"is_observed":false,"is_religious":false,"type":"national holiday"},{"name":"All Saints' Day","date":{"month":11,"day":1},"formattedDate":"1 Nov","weekday":{"numeric":6,"name":"Saturday"},"is_public":false,"is_observed":false,"is_religious":true,"type":"national holiday, christian"},{"name":"December Solstice","date":{"month":12,"day":21},"formattedDate":"21 Dec","weekday":{"numeric":7,"name":"Sunday"},"is_public":false,"is_observed":false,"is_religious":false,"type":"season"},{"name":"Christmas Eve","date":{"month":12,"day":24},"formattedDate":"24 Dec","weekday":{"numeric":3,"name":"Wednesday"},"is_public":false,"is_observed":false,"is_religious":false,"type":"half day holiday"},{"name":"Christmas Day","date":{"month":12,"day":25},"formattedDate":"25 Dec","weekday":{"numeric":4,"name":"Thursday"},"is_public":false,"is_observed":false,"is_religious":true,"type":"national holiday, christian"},{"name":"New Year's Eve","date":{"month":12,"day":31},"formattedDate":"31 Dec","weekday":{"numeric":3,"name":"Wednesday"},"is_public":false,"is_observed":false,"is_religious":false,"type":"half day holiday"}]